{"c.p._2063_2020.pdf": 0.07, "HRC7734-G_1003-GOF2009[UrduTranslation].pdf": 0.09, "H.R.C.19of1996[AsgharKhanCase]DetailedReasons.pdf": 0.07, "HRC7734-G_1003-GOF2009[AllegedCorruptionInRentalPowerPlants].pdf": 0.1, "c.a._749_2021.pdf": 0.12, "cma.3685-3686_of_2012_in_hrc.7734-g_of_2009_dt_31.01.2013.pdf": 0.09, "crl.p._47_p_2017.pdf": 0.07, "cp784of2013.pdf": 0.08, "Const.P.115-2012etc.pdf": 0.13, "h.r.c._318_1993.pdf": 0.08, "c.a._513_2014.pdf": 0.1, "c.p._2032_2019.pdf": 0.07, "CAs.149-150of2010.pdf": 0.11, "hrc.14392of2013-01.07.2013.pdf": 0.43, "Const.P.20of2013-dt-28-6-2013.pdf": 0.08, "h.r.c._20883_2018.pdf": 0.11, "Const.PetitionNo.30of2013-dt-4-6-2013.pdf": 0.1, "Const.P.67of2011-dt-10.6.2013.pdf": 0.07, "hrc.14392_2013.pdf": 0.38, "HRC.14392of2013.pdf": 0.15}