{"date": ["january", "june", "april", "day", "issuance", "december", "november", "october", "september", "march"], "day": ["month", "week", "hour", "thirty", "ninety", "year", "sixty", "expiration", "period", "expiry"], "damage": ["loss", "harm", "inconvenience", "irreparable", "hardship", "colossal", "destruction", "injustice", "risk", "liquidate"], "daughter": ["sister", "son", "wife", "mother", "widow", "husband", "father", "uncle", "cousin", "maternal"], "daily": ["dawn", "jang", "newspaper", "news", "clipping", "wager", "waqt", "mashriq", "widely", "patriot"], "dag": ["apg", "aag", "agp", "aagp", "sr", "amici", "addl", "amicus", "curia", "pga"], "datum": ["documentation", "map", "chart", "funding", "information", "statistic", "scientific", "material", "data", "nadra"], "danger": ["confusion", "tendency", "threat", "constant", "disease", "imminent", "likelihood", "apprehension", "repercussion", "magnitude"], "dar": ["mingora", "qaza", "uloom", "tando", "abidin", "aman", "mulk", "khairi", "asstt", "qadeer"], "dangerous": ["harden", "desperate", "insecurity", "retaliation", "disorder", "hurt", "intimidation", "perfect", "capture", "weak"], "daniel": ["pearl", "decease", "abductee", "pw", "mai", "salma", "bibi", "qari", "churri", "mufiya"], "dam": ["runway", "tank", "drainage", "underground", "km", "lake", "river", "indus", "storage", "bridge"], "dawn": ["jang", "daily", "waqt", "clipping", "news", "aaj", "nawa", "flash", "mashriq", "ary"], "dacoity": ["robbery", "gang", "brutal", "gruesome", "kidnapping", "murder", "rape", "hijacking", "offense", "abduction"], "dad": ["badshah", "zada", "gul", "saifullah", "khuda", "bukhsh", "ghazala", "khatoon", "ikramullah", "farida"], "database": ["saving", "card", "shipping", "nadra", "highway", "broadcasting", "kuwait", "refinery", "ndma", "fertilizer"], "dacca": ["lah", "kar", "fsc", "pesh", "jour", "madras", "patna", "bom", "nagpur", "mad"], "daman": ["arsh", "diyat", "fine", "amounting", "instalment", "tune", "ri", "differential", "remainder", "stipend"], "dark": ["front", "night", "mosque", "captivity", "darkness", "cold", "mid", "proximity", "shock", "grip"], "dairy": ["jute", "poultry", "vegetable", "ahmedabad", "refining", "products", "ghee", "leather", "kohinoor", "chenab"], "daylight": ["neighbourhood", "dark", "happening", "tragic", "faction", "rage", "scatter", "thoroughfare", "episode", "darkness"], "das": ["gupta", "pandey", "chandra", "narain", "swami", "madan", "ashok", "shetty", "chowdhry", "narayan"], "dastoor": ["tahafaz", "barai", "thafaz", "chowdhry", "prasad", "mahaz", "wukala", "narain", "raj", "quader"], "dagger": ["hatchet", "knife", "rifle", "kalashnikov", "gun", "pistol", "stab", "sota", "kalashnikovs", "shoot"], "dawood": ["younas", "tufail", "ishaque", "kakar", "hanif", "panhwar", "boota", "mansha", "yasin", "rafiq"], "dae": ["diploma", "pipfa", "ba", "bachelor", "judgeship", "sfs", "graduation", "ls", "phil", "fcp"], "data": ["cdr", "recorder", "digital", "clipping", "pk", "satellite", "exhs", "computer", "classified", "twitter"], "darkness": ["shroud", "night", "scuffle", "corolla", "tear", "suddenly", "trap", "bleed", "mystery", "dark"], "danish": ["shigri", "burhan", "imtiaz", "atif", "amjad", "meer", "shoukat", "taimur", "farrukh", "dy"], "dadu": ["haripur", "muzaffargarh", "saddar", "zhob", "kasur", "jhang", "bahawalnagar", "mandi", "nowshera", "talagang"], "dastagir": ["zaki", "owais", "farid", "mohal", "jally", "wattoo", "rasul", "puri", "charle", "maneka"], "daud": ["shabir", "sarwar", "yaseen", "arbab", "yaqoob", "tufail", "farid", "sarfraz", "zubair", "ishfaq"], "dare": ["brigade", "devil", "graze", "maher", "mina", "maltreat", "shame", "chakra", "gharo", "usama"], "damaging": ["panic", "ransack", "arson", "looting", "mafia", "deception", "devastating", "destruction", "humiliation", "rebellion"], "dacoit": ["churri", "dagger", "stab", "knife", "instigate", "lover", "bombing", "shotgun", "baradari", "butcher"], "dada": ["warraich", "moazzam", "jah", "spl", "talpur", "fahim", "sameen", "mna", "mana", "qamar"], "dated": ["dac", "malkiat", "bcd", "che", "tejori", "js", "coord", "rakkar", "shajra", "esse"], "david": ["paley", "nandla", "wa", "bhullay", "butler", "banay", "shami", "wal", "kutub", "ja"], "darya": ["di", "behram", "iman", "adam", "akhunzada", "junejo", "asadullah", "mohabbat", "roedad", "gujar"], "daraz": ["hayat", "farooq", "rehan", "hazrat", "zubair", "naveed", "ashfaq", "zaman", "asim", "tahir"], "dastgir": ["rasool", "rasul", "mustafa", "mohiuddin", "farid", "mohyuddin", "nabi", "fareed", "murtaza", "hyder"], "dasti": ["raoof", "mahar", "wasay", "majid", "majee", "wahid", "makki", "razak", "misbahuddin", "samad"], "darbar": ["nishtar", "rakh", "kashmore", "rhc", "gharo", "matiari", "hafizabad", "bombing", "dari", "kv"], "dayo": ["qurban", "pyar", "liaqat", "riasat", "mehar", "ashtar", "ausaf", "barkat", "gohar", "fazli"], "darul": ["kafala", "khas", "utman", "kha", "sumbal", "jalalpur", "reimer", "lidhar", "beixin", "amanulah"], "daewoo": ["calicut", "tata", "khewra", "airlines", "cld", "hindustan", "ahmedabad", "kohinoor", "laboratories", "burmah"], "dadan": ["pind", "ghazi", "lashkar", "kehar", "faridullah", "miran", "mandokhel", "khamiso", "rahimyar", "ajab"], "dayaram": ["ramana", "shetty", "farhum", "pandey", "saksena", "narayana", "amal", "hock", "mahamadi", "narayan"], "dal": ["jaw", "bakht", "ambreen", "kharadar", "fakhruddin", "lee", "muhammadi", "ja", "zeb", "sipra"], "darakhshan": ["utman", "phalia", "lass", "sab", "beixin", "basin", "bhiria", "aluminum", "mirpurkhas", "mo"], "dat": ["sharafi", "rakkar", "lass", "mallah", "ja", "dorf", "kulsoom", "ki", "hippocrate", "nandla"], "dairie": ["knitwear", "caveator", "nhrc", "fabrics", "julius", "ufone", "pcc", "razvi", "reposte", "br"], "darshan": ["walker", "ramana", "bandhua", "vineet", "wadhwa", "kishan", "phulphoto", "morcha", "hay", "nixon"], "danas": ["berlex", "bahuman", "bahrain", "aluminum", "sambu", "sukh", "chenab", "pharma", "motors", "bara"], "dams": ["bhasha", "diamer", "onshore", "beixin", "honorarium", "xinjiang", "dgpc", "wppo", "mo", "aud"], "dajag": ["zaid", "khalili", "temuri", "spl", "eco", "sayyidna", "asst", "amna", "ammar", "hrm"], "dassu": ["pattan", "taluka", "kalan", "mansehra", "mouza", "tehsil", "kohistan", "okara", "syedan", "swat"], "dargai": ["sohbatpur", "raiwind", "kv", "weaving", "pine", "rawal", "wah", "shahi", "eminabad", "manga"], "daw": ["pone", "ganga", "venkata", "bakka", "khairu", "nair", "vithaldas", "saksena", "gula", "samano"], "dara": ["sepco", "inv", "utman", "lpgcl", "samoo", "eshaq", "jalalpur", "sarai", "saiful", "aug"], "darwesh": ["zahur", "kadri", "nandla", "ee", "rai", "campbell", "uksc", "ilahi", "dina", "ji"], "damocle": ["simplification", "wooden", "chaddar", "sword", "monastery", "perchis", "spill", "nose", "unpolluted", "dioxide"], "daryoba": ["sivan", "patiala", "shagufta", "supl", "maharaj", "sadasivan", "thachambalath", "swamiar", "riazuddin", "hazro"], "dash": ["methamphetamine", "aug", "utman", "sharafi", "nishtar", "paver", "egg", "romana", "chawla", "millat"], "danishwar": ["sumera", "sumaira", "respondents", "wains", "fattah", "asst", "ayoub", "sangha", "allawala", "maliha"], "daudzai": ["bhalwal", "utman", "gatron", "bhiria", "burewala", "sadasivan", "eng", "magis", "jalalpur", "taiser"], "dac": ["supl", "nrsp", "bb", "malkiat", "jr", "sibnath", "aug", "eidgah", "dm", "suppl"], "dawud": ["sunan", "kitab", "anfal", "abdallah", "wa", "\u0639\u0644\u064a\u0647", "cairo", "kutub", "tirmidhi", "beirut"], "damaged": ["takbeer", "samson", "americans", "dero", "butane", "handbill", "shrub", "jagjit", "airplane", "thirtha"], "dangerously": ["imsb", "butterworth", "breaker", "jungle", "perpetuation", "favourtism", "inflammable", "eastern", "ramanatha", "flora"], "daska": ["utman", "jalalpur", "shagufta", "sarai", "bhalwal", "gatron", "supl", "sufian", "applause", "nakara"], "damn": ["gascoigne", "brilliant", "khala", "applause", "stole", "tayyeba", "tulsiram", "mindboggle", "ghausan", "unthinkable"], "daesh": ["scattered", "subscriber", "shopkeeper", "ptap", "plate", "turkmenistan", "tap", "shell", "heap", "nicop"], "dap": ["kv", "dari", "paver", "chaddar", "oven", "utman", "mo", "kabul", "selab", "egg"], "daly": ["tabari", "wa", "abidin", "kitab", "francis", "carter", "shami", "anfal", "beirut", "abdallah"], "dan": ["zargham", "ihsanullah", "pathak", "saksena", "faheemuddin", "haidar", "eshaq", "abbott", "shree", "aero"], "dahrki": ["utman", "chawla", "beixin", "tulsiram", "khail", "portugal", "sharafi", "dm", "saf", "jandran"], "darakshan": ["darakhshan", "saddar", "aps", "nazimabad", "bhiria", "ferozwala", "chiniot", "kashmore", "dara", "hazro"], "dari": ["lass", "bombing", "rakkar", "dat", "sharafi", "utman", "banaras", "nishtar", "raju", "hygiene"], "dawakhana": ["nooruddin", "badrul", "sameena", "khalida", "summation", "cps", "madhavji", "wakeel", "perveen", "dharasibhai"]}