{"eighteenth": ["nineteenth", "eighth", "seventeenth", "fourteenth", "twentieth", "lfo", "insertion", "insert", "amendment", "introduce"], "eighth": ["seventeenth", "nineteenth", "eighteenth", "fourteenth", "twentieth", "lfo", "tenth", "sixth", "ninth", "coca"], "eia": ["iee", "update", "monitoring", "periodic", "feasibility", "nespak", "adb", "periodically", "analytical", "testing"], "eighty": ["seventy", "lakh", "fifty", "hundred", "forty", "thousand", "approximately", "paisa", "tola", "cubic"], "eighteen": ["sixteen", "aged", "barely", "nineteen", "eleven", "ago", "ramadan", "twelve", "mashriq", "seventy"], "eid": ["fitr", "ramadan", "tehran", "akhri", "winter", "getting", "sixty", "onset", "socrate", "mouqa"], "eidain": ["orient", "stopgap", "azan", "timely", "happiness", "internship", "jumma", "unhygienic", "bds", "belate"], "eidgah": ["aug", "ja", "rakkar", "supl", "beixin", "saf", "allawala", "chawla", "magis", "kcy"]}