{"Const.P.33_2013.pdf": {"8": 4.314}, "C.R.P._125_2014.pdf": {"44": 4.314}, "smc.18_2010_final.pdf": {"72": 4.314}, "C.A._2109_2016.pdf": {"2": 4.314}, "Const.PetitionNo.77of2010_31.10.2012.pdf": {"7": 4.314}, "C.A._704_2017.pdf": {"8": 4.314}, "C.A._417-L_2009.pdf": {"2": 4.314}, "c.a._18_k_2021.pdf": {"5": 4.314}, "c.p._1290_l_2019.pdf": {"10": 4.314}, "c.a._24_2015.pdf": {"13": 4.314}, "C.R.P.193of2013.pdf": {"44": 4.314}, "C.A._1540_2006.pdf": {"1": 4.314}, "c.r.p._421_2020.pdf": {"3": 4.314}, "C.A._585_2018.pdf": {"3": 30.1977, "2": 30.1977}, "const.p._21_2023_11082023.pdf": {"14": 4.314}, "c.a._469_2021.pdf": {"6": 4.314}, "const.p._39_16122019.pdf": {"37": 4.314}, "C.P._2297_2018.pdf": {"1": 4.314}, "crl.p._713_l_2020.pdf": {"1": 4.314}, "c.a._1476_2018.pdf": {"49": 4.314}, "const.p._13_2023_09052023.pdf": {"4": 8.6279}, "c.p._546_2021.pdf": {"6": 4.314}, "c.p._3933_2023.pdf": {"4": 4.314}, "C.P._1958_2016.pdf": {"1": 4.314}, "C.M.A._376-K_2014.pdf": {"93": 4.314}, "c.a._49_2022.pdf": {"1": 8.6279}, "const.p._10_2020.pdf": {"1": 4.314}, "C.M.A.4918of2012-dt-26-4-2013.pdf": {"4": 4.314}, "const.p._39_2019.pdf": {"37": 4.314}, "C.A._79_P_2013.pdf": {"1": 4.314}, "c.m.a._1243_2021_04042022.pdf": {"6": 4.314}, "CJD_Section 2-A_Case_as_on_26_06_2006.pdf": {"23": 4.314}, "c.p._2892_2020.pdf": {"2": 4.314}, "C.M.A._8215_2016.pdf": {"89": 4.314}}