{"c.a._1476_2018_urdu.pdf": {"17": 6.1572, "11": 6.1572}, "ConstitutionPetitionNo21OF2007.pdf": {"164": 6.1572, "71": 6.1572, "141": 6.1572}, "cma.5959_2013.pdf": {"6": 6.1572, "7": 6.1572}, "NRO_Judgment.pdf": {"271": 6.1572}, "Const.P.40of2012-DetailJudgment[UrduTranslation]-dt-3.7.2012.pdf": {"39": 6.1572}, "Const.P._50_2018.pdf": {"47": 6.1572}, "Const.P.12of2010.pdf": {"164": 6.1572, "803": 6.1572, "157": 6.1572, "136": 6.1572, "131": 6.1572}, "Const.P.12of2010Urdu.pdf": {"1": 6.1572, "31": 6.1572}, "Const.P._29_2016.pdf": {"149": 6.1572}, "smc.18_2010_final.pdf": {"96": 6.1572}, "Const.P._36_2016_dt_15_12_2017.pdf": {"6": 6.1572}, "Const.P.30of2013.pdf": {"36": 6.1572}, "H.R.C.19of1996[AsgharKhanCase]DetailedReasonsUrduTranslation.pdf": {"123": 6.1572, "26": 6.1572, "118": 12.3145, "124": 12.3145}, "s.m.c._1_2022_detailed.pdf": {"68": 6.1572}, "H.R.C.19of1996[AsgharKhanCase]DetailedReasons.pdf": {"105": 6.1572, "84": 6.1572, "120": 6.1572, "124": 12.3145}, "smc_1_2014.pdf": {"55": 6.1572}, "Const.P.77-78-79 [Memogate]DetailedOrder.pdf": {"67": 6.1572}, "Crl.A._39_L_2015_Urdu.pdf": {"49": 6.1572, "55": 6.1572, "53": 6.1572}, "JR_Judgment_on_17th_Amendmend_and_Presidents_Uniform_Case.pdf": {"16": 6.1572}, "Const.P.56_2003_U_dt_8-9-2015.pdf": {"3": 6.1572}, "Crl.O.P.89of2011.pdf": {"91": 6.1572}, "s.m.c._1_2023_01032023.pdf": {"4": 6.1572}, "CMA1362OF2012-DT-10-04-2012.pdf": {"8": 6.1572}, "Crl.A._1-K_2018.pdf": {"13": 6.1572}, "c.r.p._296_2020_04022022.pdf": {"85": 6.1572}, "HRC-4668of2006.pdf": {"39": 6.1572}, "c.a._797_2013.pdf": {"3": 6.1572}, "C.A._1428_2016.pdf": {"27": 6.1572}, "Const.P.77-2011[MemoScandal]dt.30.12.2011.pdf": {"2": 6.1572}, "c.r.p._292_2021_detailed.pdf": {"25": 6.1572}, "const.p._17_2019_detailed_reasoning.pdf": {"121": 6.1572}, "const.p._39_16122019.pdf": {"15": 6.1572}, "C.A._654_2010.pdf": {"8": 6.1572}, "c.p._1125_2018.pdf": {"3": 6.1572}, "const.p._6_2023_dt_05_01_2023.pdf": {"1": 6.1572}, "const.p._24_2023_f.pdf": {"60": 6.1572}, "ca.297_2014.pdf": {"4": 6.1572}, "smc.16of2011.pdf": {"6": 6.1572}, "C.A.39_2010.pdf": {"24": 6.1572}, "c.r.p._35_k_2020.pdf": {"4": 6.1572}, "JR_Varan_Case.pdf": {"5": 6.1572}, "JR_The_State_through_NAB_VS_Haji_Nasim-ur-Rehman.pdf": {"14": 6.1572}, "C.P._529_2015.pdf": {"39": 6.1572}, "c.p._659_2019.pdf": {"4": 6.1572}, "c.a._1685_2021.pdf": {"7": 6.1572}, "const.p._39_2019.pdf": {"15": 6.1572}, "c.p._32_q_2019.pdf": {"7": 6.1572}, "C.P._2167_2014.pdf": {"3": 6.1572}, "cma.6882-13.pdf": {"2": 6.1572}, "crl.a.264_2006.pdf": {"42": 6.1572}}