{"c.a._1079_2015.pdf": {"9": 7.4175}, "18TH_AMENDMENT_ORDER.pdf": {"13": 7.4175}, "S.M.C.18_2016_dt_06_01_2017.pdf": {"7": 7.4175}, "c.a._1660_2014.pdf": {"1": 7.4175}, "c.a._497_2020.pdf": {"8": 7.4175}, "C.A._1171_2017.pdf": {"11": 7.4175, "8": 7.4175}, "Const.P._24_2012.pdf": {"25": 7.4175}, "Const.P.87of2011.pdf": {"7": 7.4175}, "crl.p._1485_l_2019.pdf": {"4": 7.4175}, "Const.Petition.24_2011_dt02062011.pdf": {"18": 7.4175}, "C.A._125_K_2016_JPMC_Dissenting_Note.pdf": {"25": 7.4175}, "C.P._842_2016.pdf": {"91": 7.4175, "130": 7.4175}, "crl.a._120_2019.pdf": {"44": 7.4175}, "Const.P.22of2013.pdf": {"38": 7.4175}, "SMCNo25of2009.pdf": {"30": 7.4175}, "c.a._52_k_2022.pdf": {"2": 7.4175}, "HR8340OF2010.pdf": {"28": 7.4175}}