{"Const.P.127of2012.pdf": {"163": 5.5099}, "Const.P.105-2012-eng-urd.PDF": {"22": 5.5099}, "C.P.796of2007-UrduTranslation-dt-10-5-2013.pdf": {"28": 5.5099, "20": 5.5099, "27": 5.5099}, "C.M.A._3854_2014_dt_17-04-2015.pdf": {"16": 5.5099}, "CONST.P.77OF2010-DT-05.04.12[URDU].pdf": {"5": 5.5099}, "URDU_CONST.P.05-2012-20.09.12.pdf": {"9": 5.5099, "8": 5.5099}, "Const.P._38_2016.pdf": {"33": 5.5099}, "NRO_Judgment.pdf": {"87": 5.5099, "186": 5.5099, "254": 5.5099}, "C.A._3_2018_dt-14-9-2018.pdf": {"29": 5.5099, "37": 5.5099}, "Const.P._50_2018.pdf": {"102": 5.5099, "84": 5.5099}, "Const.P.12of2010.pdf": {"503": 5.5099, "105": 5.5099}, "Const.P.87of2011[UrduVersion].pdf": {"48": 5.5099, "44": 5.5099, "52": 5.5099}, "Const.P.12of2010Urdu.pdf": {"26": 5.5099}, "S.M.C._20_2016.pdf": {"8": 5.5099}, "Const.P._29_2016.pdf": {"109": 5.5099}, "smc.18_2010_final.pdf": {"59": 5.5099, "85": 5.5099}, "C.A._3_2018.pdf": {"29": 5.5099, "37": 5.5099}, "Urdu-Const.P-77-2010-12.10.2012.pdf": {"35": 5.5099, "23": 5.5099}, "ICA-1OF2012-UrduTranslation.pdf": {"2": 5.5099}, "Const.P._36_2016_dt_15_12_2017.pdf": {"34": 5.5099}, "Const.P.40of2012-AdditionalNoteofJusticeJawwadSKhawaja.pdf": {"3": 5.5099, "1": 5.5099}, "S.M.C.24of2010[urdu-version].pdf": {"14": 5.5099, "16": 5.5099, "12": 5.5099, "6": 5.5099}, "CAA_25.09.2013.pdf": {"7": 5.5099}, "H.R.C.19of1996[AsgharKhanCase]DetailedReasonsUrduTranslation.pdf": {"96": 5.5099}, "s.m.c._1_2022_detailed.pdf": {"23": 5.5099}, "SMC16of2011_detailed_judgment.pdf": {"57": 5.5099, "83": 5.5099}, "CMA1362OF2012-DT-10-04-2012[URDU].pdf": {"10": 5.5099, "5": 5.5099}, "C.R.P.167of2012-dt-30-8-2012.pdf": {"14": 5.5099}, "Const.P.46of2013-dt-27-12-2013.pdf": {"23": 5.5099}, "smc_1_2014.pdf": {"54": 5.5099, "44": 5.5099}, "C.P.796of2007-dt-10-5-2013.pdf": {"177": 5.5099, "176": 5.5099, "169": 5.5099}, "JR_Judgment_on_17th_Amendmend_and_Presidents_Uniform_Case.pdf": {"51": 5.5099}, "C.P._1515_2016.pdf": {"2": 5.5099}, "crl.a._03_p_2017.pdf": {"9": 5.5099}, "Const.P.77of2010-DT-05-04-2012.pdf": {"7": 5.5099}, "CJD_Reference by_the_President_of_Pakistan_under_Article_186.pdf": {"75": 11.0198}, "Const.P.56_2003_U_dt_8-9-2015.pdf": {"14": 5.5099, "3": 5.5099}, "crp.328-329_2013.pdf": {"58": 5.5099}, "Crl.O.P.89of2011.pdf": {"100": 5.5099}, "C.P._731_K_2018.pdf": {"4": 5.5099}, "C.A._353_2015.pdf": {"14": 5.5099}, "s.m.c._1_2023_31mar2023.pdf": {"6": 5.5099}, "c.r.p._421_2020_dissenting_notes.pdf": {"10": 5.5099}, "c.m.a._7084_2020_opinion_hj_5.pdf": {"4": 5.5099}, "CMA No.5144of2011.pdf": {"3": 5.5099}, "C.P._78_K_2015.pdf": {"5": 11.0198}, "c.r.p._296_2020_04022022.pdf": {"48": 5.5099}, "c.a._446_2021.pdf": {"14": 5.5099}, "JR_Detailed_Judgment_in_Referendum_Case.pdf": {"29": 5.5099, "13": 5.5099, "49": 5.5099, "9": 5.5099}, "const.p._2_2022_14102022.pdf": {"29": 5.5099, "48": 5.5099}, "C.A._1171_2017.pdf": {"28": 5.5099}, "C.A._359_2013.pdf": {"8": 5.5099}, "const.p.9_2014_detail_reasons.pdf": {"10": 5.5099}, "JR_Constitution_Petition_No._15_17-24_and_512_of_2002.pdf": {"5": 5.5099, "6": 5.5099}, "Const.P._2_2011.pdf": {"37": 5.5099}, "c.a._1095_2018_13092019.pdf": {"23": 5.5099}, "const.p._17_2019_detailed_reasoning.pdf": {"49": 5.5099}, "C.A._139_2013.pdf": {"5": 5.5099}, "Const.Petition.24_2011_dt02062011.pdf": {"6": 5.5099}, "C.A._25_K_2018.pdf": {"2": 11.0198}, "Const.P.No.33and34of2005-dt-27-6-2013.pdf": {"38": 5.5099}, "const.p.5_2011.pdf": {"22": 5.5099}, "c.p._34_2022.pdf": {"6": 5.5099}, "c.a._350_2020.pdf": {"2": 5.5099}, "Const.P._29_2017.pdf": {"24": 5.5099}, "C.A._1264_2006.pdf": {"6": 5.5099}, "C.A._26_K_2018.pdf": {"1": 5.5099}, "c.p._4740_2017.pdf": {"3": 5.5099}, "c.m.a._7084_2020.pdf": {"23": 5.5099}, "c.a._1481_2015.pdf": {"12": 5.5099}, "S.M.C._3_2018.pdf": {"39": 5.5099}, "C.A._767_2014.pdf": {"15": 11.0198}, "Crl.A._35_K_2016.pdf": {"7": 5.5099}, "c.r.p._296_2020_hj10.pdf": {"8": 5.5099}, "const.p._24_2023_f.pdf": {"36": 5.5099}, "c.p._4725_2018.pdf": {"2": 5.5099}, "c.p._546_2021.pdf": {"6": 5.5099}, "I.C.A._4_2017.pdf": {"49": 5.5099}, "c.a._925_2020.pdf": {"1": 5.5099}, "C.A._843_2012.pdf": {"9": 5.5099, "18": 5.5099}, "C.P._80_2018.pdf": {"2": 5.5099}, "C.A._1086_2009.pdf": {"9": 5.5099}, "c.a._152_l_2010.pdf": {"6": 5.5099}, "c.a._52_k_2022.pdf": {"7": 5.5099}, "c.p._6117_2021.pdf": {"4": 5.5099}, "C.M.A.6309_2018_14072018.pdf": {"2": 5.5099}, "c.a._429_2020.pdf": {"14": 5.5099}, "C.M.A_687_2017.pdf": {"3": 5.5099}, "C.A._845_2010.pdf": {"13": 5.5099, "8": 5.5099}, "Criminal_Original_P93to98.pdf": {"4": 5.5099}, "CJD_Section 2-A_Case_as_on_26_06_2006.pdf": {"75": 11.0198}, "C.P._3181_2015.pdf": {"3": 5.5099}, "c.p._590_2021.pdf": {"3": 5.5099}, "HR8340OF2010.pdf": {"27": 5.5099}, "c.a._196_p_2014_13062023.pdf": {"12": 5.5099}, "c.a._764_2021.pdf": {"8": 5.5099}, "Const.P.5and15-HRC14144-DetailedReasons.pdf": {"63": 5.5099, "56": 5.5099}}