{"crl.p.240_2012.pdf": {"2": 2.0877}, "Crl.O.P._09_2018.pdf": {"10": 2.0877}, "H.R.C.No.19of1996DT19-10-2012[UrduTranslation].pdf": {"3": 2.0877}, "c.p._3224_2019.pdf": {"9": 2.0877}, "Const.P.12of2010.pdf": {"610": 58.4567, "409": 58.4567}, "Const.P._29_2016.pdf": {"236": 16.7019}, "c.p._2243_l_2019.pdf": {"41": 2.0877}, "Const.P._36_2016_dt_15_12_2017.pdf": {"52": 2.0877}, "S.J.C_347_2018.PDF": {"11": 6.2632}, "Ref.01_2012_addl.note_HJ.ejaz_afzal_khan.pdf": {"60": 2.0877}, "H.R.C.19of1996[AsgharKhanCase]DetailedReasonsUrduTranslation.pdf": {"136": 2.0877}, "SMC16of2011_detailed_judgment.pdf": {"141": 6.2632}, "c.a._10_2020.pdf": {"4": 4.1755}, "CP778-779.pdf": {"44": 8.351}, "crp.328-329_2013.pdf": {"45": 12.5264}, "HRC7734-G_1003-GOF2009[AllegedCorruptionInRentalPowerPlants].pdf": {"66": 4.1755}, "c.p._2855_2017.pdf": {"2": 2.0877}, "const.p._24_2017.pdf": {"26": 2.0877}, "crl.m.a._62_p_2018.pdf": {"6": 4.1755}, "crl.p._231_2020.pdf": {"3": 4.1755}, "c.a._1767_2019.pdf": {"5": 4.1755}, "c.a._2150_2019.pdf": {"17": 2.0877}, "c.p._1874_2022.pdf": {"3": 2.0877}, "c.a._754_2020.pdf": {"7": 2.0877}, "c.p._1877_l_2016.pdf": {"4": 2.0877}, "Crl.A_04-K_2012.pdf": {"4": 2.0877}, "C.R.P._94_2014.pdf": {"4": 4.1755}, "h.r.c_11827_s_2018.pdf": {"5": 8.351}, "Crl.P.200of2009.pdf": {"39": 12.5264}, "C.A._725_2008.pdf": {"7": 2.0877}, "S.M.C._03_2017.pdf": {"24": 4.1755}, "const.p._17_2019_detailed_reasoning.pdf": {"10": 39.6671, "70": 39.6671}, "c.m.a._490_2021_11022021.pdf": {"3": 2.0877}, "crl.p._654_2020.pdf": {"2": 2.0877}, "c.p._2032_2019.pdf": {"3": 6.2632}, "const.p.6_2011_final.pdf": {"26": 2.0877}, "S.M.C._8_2018.pdf": {"14": 2.0877}, "ConstitutionPetitionNo39of2009.pdf": {"28": 2.0877}, "C.P._1774_2014.pdf": {"14": 2.0877}, "c.p._3989_2022.pdf": {"2": 12.5264}, "Crl.O.P.6of2012.pdf": {"63": 2.0877}, "crl.p._443_l_2020_dissenting_note.pdf": {"6": 4.1755}, "s.m.c._4_2021.pdf": {"4": 2.0877}, "JR_Fecto_Belarus_Tractor_Limited_Case.pdf": {"43": 4.1755}, "crl.p._950_2021.pdf": {"2": 2.0877}, "c.p._3249_2015.pdf": {"20": 2.0877}, "c.p._4980_2021.pdf": {"2": 4.1755}}