{"ConstitutionPetitionNo21OF2007.pdf": {"263": 8.1582, "262": 8.1582}, "Const.P._134_2012.pdf": {"14": 24.4747, "8": 24.4747}, "Const.P_6of2011.pdf": {"4": 4.0791}, "Crl.A._39_L_2015.pdf": {"9": 4.0791}, "C.A._2215_2006.pdf": {"1": 8.1582}, "Const.P._29_2016.pdf": {"95": 4.0791}, "SMC16of2011_detailed_judgment.pdf": {"32": 4.0791}, "crl.a._528_2019.pdf": {"3": 8.1582, "1": 8.1582}, "Crl.A._39_L_2015_Urdu.pdf": {"12": 4.0791}, "CJD_Reference by_the_President_of_Pakistan_under_Article_186.pdf": {"14": 4.0791}, "Crl.P.163_to_171_S.M.C.5_2005.pdf": {"75": 12.2373, "50": 12.2373, "53": 12.2373}, "18TH_AMENDMENT_ORDER.pdf": {"5": 4.0791}, "c.p._490_k_2020.pdf": {"11": 4.0791}, "c.a._1002_2015.pdf": {"7": 4.0791}, "Crl.A.140of2005.pdf": {"9": 8.1582, "2": 8.1582}, "c.a._1095_2018_13092019.pdf": {"28": 4.0791}, "c.r.p._421_2020.pdf": {"5": 4.0791}, "c.a.1540-1599_2013.pdf": {"3": 4.0791}, "C.R.P._335_2014.pdf": {"2": 4.0791}, "C.A._1086_2014.pdf": {"8": 4.0791}, "crl.a._208_2022.pdf": {"2": 4.0791}, "smc_16_23.06.2014.pdf": {"2": 4.0791}, "c.p._469_l_2023.pdf": {"1": 4.0791}, "crl.a._319_l_2017.pdf": {"1": 8.1582}, "Const.P.77of2010-dt-21-12-2012.pdf": {"9": 4.0791}, "c.a._1113_2017.pdf": {"13": 8.1582, "23": 8.1582}, "CJD_Constitution_Petition_No_36_of_2005.pdf": {"26": 4.0791}, "c.a._49_2022.pdf": {"3": 4.0791}, "Const.P._134_2012_21012019.pdf": {"23": 24.4747, "19": 24.4747}, "crl.a._277_2020.pdf": {"1": 8.1582}, "C.A.876-879of2005.pdf": {"13": 4.0791}, "c.p._3134_2022.pdf": {"1": 4.0791}, "Crl.P.213-2013_03.07.2013.pdf": {"3": 4.0791}, "crl.p._1329_2023.pdf": {"5": 36.712, "6": 36.712, "3": 36.712}, "crl.p._440_2022 .pdf": {"1": 4.0791}, "c.a._359_2020.pdf": {"9": 4.0791}, "crl.p._273_l_2021.pdf": {"1": 4.0791}, "CJD_Section 2-A_Case_as_on_26_06_2006.pdf": {"17": 4.0791}, "H.R.C._10842_P_2018.pdf": {"8": 8.1582, "7": 8.1582}, "c.a._1399_2019.pdf": {"2": 8.1582, "1": 8.1582}, "C.R.P._309_2013.pdf": {"3": 4.0791}, "Const.P.57 _2016.pdf": {"2": 4.0791}, "JR_Fecto_Belarus_Tractor_Limited_Case.pdf": {"8": 4.0791}}