{"c.a._1476_2018_urdu.pdf": {"11": 6.1875}, "Crl.P._9-P_2016.pdf": {"2": 6.1875}, "crl.a._400_2019.pdf": {"9": 6.1875}, "H.R.C.No.19of1996DT19-10-2012[UrduTranslation].pdf": {"5": 12.3751}, "Crl.A._609_2014.pdf": {"7": 6.1875}, "NRO_Judgment.pdf": {"165": 6.1875}, "C.M.A.64of2013dt-12-3-2013.pdf": {"9": 6.1875}, "Const.P.40of2012-DetailJudgment[UrduTranslation]-dt-3.7.2012.pdf": {"29": 6.1875, "41": 6.1875}, "Const.P.12of2010.pdf": {"791": 6.1875}, "Const.P.87of2011[UrduVersion].pdf": {"50": 6.1875, "35": 6.1875}, "CMA_1145-K_2013_in_SMC_16-2011_08-03-2013.pdf": {"19": 6.1875}, "Const.P.12of2010Urdu.pdf": {"17": 6.1875, "37": 6.1875, "24": 6.1875}, "Const.P.33_2013.pdf": {"37": 6.1875}, "Const.PetitionNo.77of2010_12.10.2012.pdf": {"54": 6.1875}, "Urdu-Const.P-77-2010-12.10.2012.pdf": {"38": 6.1875, "43": 6.1875, "41": 6.1875, "35": 24.7501, "36": 74.2504}, "Const.P.40of2012-AdditionalNoteofJusticeJawwadSKhawaja.pdf": {"2": 6.1875}, "Crl.A._275_2011.pdf": {"3": 6.1875}, "S.M.C.24of2010[urdu-version].pdf": {"6": 6.1875}, "CMA_1145-K_2013_in_SMC_16-2011_06-03-2013.pdf": {"11": 6.1875}, "Const.P.NO.62OF2010_orderdt06062011.pdf": {"17": 6.1875}, "H.R.C.19of1996[AsgharKhanCase]DetailedReasonsUrduTranslation.pdf": {"14": 12.3751, "138": 12.3751, "122": 6.1875, "123": 6.1875}, "s.m.c._1_2022_detailed.pdf": {"15": 6.1875, "11": 6.1875, "90": 6.1875, "32": 6.1875}, "Const.PetitionNo.77of2010_31.10.2012.pdf": {"8": 6.1875}, "SMC16of2011_detailed_judgment.pdf": {"150": 6.1875, "134": 6.1875, "132": 6.1875}, "crl.a._95_2019.pdf": {"20": 6.1875}, "HRC7734-G_1003-GOF2009[UrduTranslation].pdf": {"60": 6.1875}, "c.p.2132_2014_with_urdu_translation.pdf": {"1": 6.1875}, "CJD_Reference by_the_President_of_Pakistan_under_Article_186.pdf": {"70": 6.1875}, "crl.p._299_2020_01042020.pdf": {"5": 6.1875}, "JR_Detailed_Judgment_in_Graduation_Qualification_Case.pdf": {"23": 6.1875}, "c.m.a._7923_2019.pdf": {"7": 6.1875}, "const.p._2_2022_14102022.pdf": {"72": 6.1875}, "const.p.115_2011.pdf": {"13": 6.1875}, "c.a._421_2018.pdf": {"8": 6.1875}, "const.p._21_2022_30102023.pdf": {"8": 6.1875}, "C.A._125_K_2016_JPMC_Dissenting_Note.pdf": {"29": 6.1875, "30": 6.1875}, "C.A.269_ETC_OF_2011.pdf": {"32": 6.1875}, "const.p._6_2023_dt_05_01_2023.pdf": {"15": 6.1875}, "Const.P.91of2011Dt-23-8-2012.pdf": {"43": 6.1875}, "const.p._24_2023_f.pdf": {"44": 6.1875}, "c.p._692_2020.pdf": {"4": 6.1875}, "S.M.C.16of2011dt-22-3-2013.pdf": {"10": 6.1875}, "c.p._607_2021.pdf": {"5": 6.1875}, "c.p._1600_2021_dt_25_01_2024.pdf": {"8": 6.1875}, "c.m.a._1243_2021_04042022.pdf": {"12": 6.1875}, "crl.p._636_2022.pdf": {"6": 6.1875}, "CPs987-989OF2011-DT19.10.2011.pdf": {"62": 6.1875}, "C.A._1313_2014.pdf": {"9": 6.1875}}