{"C.P.796of2007-UrduTranslation-dt-10-5-2013.pdf": {"27": 7.3662}, "Const.P.31of2011etc.pdf": {"32": 7.3662}, "c.p._2537_2020.pdf": {"3": 7.3662}, "Const.P.40of2012-DetailJudgment[UrduTranslation]-dt-3.7.2012.pdf": {"41": 7.3662}, "CPLA_796_2007_ETC_SHORT_ORDER_REKO_DIQ_CASE.pdf": {"24": 7.3662}, "C.P.796of2007-dt-10-5-2013.pdf": {"176": 7.3662, "134": 7.3662}, "Crl.O.P.89of2011.pdf": {"127": 7.3662}, "const.p._24_2017.pdf": {"35": 7.3662}, "c.a._1518_2013.pdf": {"2": 7.3662}, "c.p._3472_2023.pdf": {"1": 7.3662}, "JR_Detailed_Judgment_in_Referendum_Case.pdf": {"14": 7.3662}, "c.a._353_2010.pdf": {"16": 7.3662}, "Const.P._2_2011.pdf": {"14": 7.3662}, "crl.p._1371_2016.pdf": {"3": 7.3662}, "reference._2_2022.pdf": {"12": 7.3662}, "crl.a._120_2019.pdf": {"13": 7.3662}, "c.a._764_2021.pdf": {"12": 7.3662}, "crl.a.264_2006.pdf": {"65": 7.3662}, "c.a._10_q_2021.pdf": {"7": 7.3662}}