{"CPs.10-18of2011.pdf": {"68": 3.9902}, "AdditionalNoteConst.P.77of2012.pdf": {"9": 3.9902}, "Const.P.33_2013.pdf": {"41": 11.9705}, "Const.PetitionNo.77of2010_12.10.2012.pdf": {"25": 3.9902}, "Urdu-Const.P-77-2010-12.10.2012.pdf": {"20": 3.9902}, "ICA-1OF2012-UrduTranslation.pdf": {"8": 3.9902}, "S.M.C.24of2010[urdu-version].pdf": {"10": 7.9803, "11": 7.9803}, "crp.328-329_2013.pdf": {"63": 7.9803, "55": 7.9803}, "C.M.A.No.19002of2012Dt-27.09.2012.pdf": {"3": 3.9902}, "c.r.p._420_2016.pdf": {"45": 7.9803}}