{"NRO_Judgment.pdf": {"111": 4.7958}, "Const.P._29_2016.pdf": {"373": 4.7958}, "Const.P.77of2012[DetailedOrderFinal].pdf": {"61": 4.7958}, "JR_Judgment_on_17th_Amendmend_and_Presidents_Uniform_Case.pdf": {"26": 4.7958}, "C.A._514_2008.pdf": {"3": 4.7958}, "c.p._167_q_2023.pdf": {"4": 4.7958}, "c.a._1000_2020.pdf": {"15": 4.7958}, "const.p._21_2023_11082023.pdf": {"24": 4.7958}, "C.A._1509_2016.pdf": {"18": 4.7958}, "c.p._3136_2022.pdf": {"3": 4.7958}, "const.p.5_2011.pdf": {"16": 4.7958}, "C.A._26_K_2018.pdf": {"2": 4.7958}, "c.a._1113_2017_dissenting_note.pdf": {"26": 4.7958}, "c.a._1498_2018.pdf": {"9": 9.5916, "7": 9.5916}, "c.a._1113_2017.pdf": {"73": 4.7958}, "const.p._9_2023.pdf": {"3": 4.7958}, "c.a._1089_2015.pdf": {"6": 4.7958}, "c.a._81_k_2022.pdf": {"8": 4.7958}, "H.R.C._17599_2018.pdf": {"9": 4.7958}, "c.a._65_k_2019.pdf": {"17": 4.7958}, "C.M.A._8215_2016.pdf": {"4": 4.7958}}