{"caseNumber": "Crl.A.6-P/2010", "caseSubject": "For Enhancement/Sessions", "caseTitle": "Alamgir v. Gul Zaman & others", "caseFileName": "Crl.A_6_P_2010.pdf", "authorJudge": "MR. JUSTICE QAZI MUHAMMAD AMIN AHMED", "judgmentText": null, "tagline": "The circumstances of the case spell out a situation that no one anticipated; once started it aggravated, resulting into injuries to both parties, with a heavier toll on the complainant\u2019s side. The liability of accused persons more aptly falls within the mischief of section 302(c), P.P.C.", "citation": "2019   SCMR  1415", "SCPCitation": "2019 SCP 112", "reported": null, "dateOfAnnouncement": "", "dateCreated": "15-05-2019", "fileSizeInBytes": 21}